kadlu/__init__.py
kadlu/index.py
kadlu/plot_util.py
kadlu/utils.py
kadlu/geospatial/__init__.py
kadlu/geospatial/interpolation.py
kadlu/geospatial/ocean.py
kadlu/geospatial/data_sources/__init__.py
kadlu/geospatial/data_sources/data_util.py
kadlu/geospatial/data_sources/era5.py
kadlu/geospatial/data_sources/gebco.py
kadlu/geospatial/data_sources/gebco_geotiff.py
kadlu/geospatial/data_sources/hycom.py
kadlu/geospatial/data_sources/load_from_file.py
kadlu/geospatial/data_sources/source_map.py
kadlu/geospatial/data_sources/wwiii.py
kadlu/sound/__init__.py
kadlu/sound/geophony.py
kadlu/sound/parabolic_equation.py
kadlu/sound/sound_speed.py
kadlu/sound/output/__init__.py
kadlu/sound/output/output_database.py
kadlu/tests/__init__.py
kadlu/tests/conftest.py
kadlu/tests/test_utils.py
kadlu/tests/geospatial/__init__.py
kadlu/tests/geospatial/test_interpolation.py
kadlu/tests/geospatial/test_ocean.py
kadlu/tests/geospatial/data_sources/__init__.py
kadlu/tests/geospatial/data_sources/test_cfg.py
kadlu/tests/geospatial/data_sources/test_era5.py
kadlu/tests/geospatial/data_sources/test_files.py
kadlu/tests/geospatial/data_sources/test_gebco.py
kadlu/tests/geospatial/data_sources/test_hycom.py
kadlu/tests/geospatial/data_sources/test_wwiii.py
kadlu/tests/sound/__init__.py
kadlu/tests/sound/test_geophony.py
kadlu/tests/sound/test_parabolic_equation.py
kadlu/tests/sound/test_sound_speed.py
kadlu/tests/sound/output/__init__.py
kadlu/tests/sound/output/test_output_dataset.py
kadlu-2.3.7.dist-info/LICENSE.txt
kadlu-2.3.7.dist-info/METADATA
kadlu-2.3.7.dist-info/WHEEL
kadlu-2.3.7.dist-info/top_level.txt
kadlu-2.3.7.dist-info/RECORD
