Metadata-Version: 2.1
Name: kadlu
Version: 2.3.7
Summary: MERIDIAN Python package for ocean ambient noise modelling
Home-page: https://gitlab.meridian.cs.dal.ca/public_projects/kadlu
Author: Oliver Kirsebom, Matthew Smith
Author-email: oliver.kirsebom@dal.ca, matthew.smith@dal.ca
License: GNU General Public License v3.0
Requires-Python: >=3.6
License-File: LICENSE.txt
Requires-Dist: Pillow
Requires-Dist: cdsapi
Requires-Dist: eccodes
Requires-Dist: gsw
Requires-Dist: imageio
Requires-Dist: matplotlib
Requires-Dist: mpl-scatter-density
Requires-Dist: netcdf4
Requires-Dist: numpy
Requires-Dist: pygrib
Requires-Dist: pyproj
Requires-Dist: requests
Requires-Dist: scipy
Requires-Dist: tqdm
Requires-Dist: xarray
